hdmf_docutils/__init__.py
hdmf_docutils/_version.py
hdmf_docutils/compare-hdf5-files.ipynb
hdmf_docutils/generate_format_docs.py
hdmf_docutils/init_sphinx_extension_doc.py
hdmf_docutils/doctools/__init__.py
hdmf_docutils/doctools/output.py
hdmf_docutils/doctools/render.py
hdmf_docutils/doctools/renderrst.py
hdmf_docutils/doctools/rst.py
hdmf_docutils-0.4.9.dist-info/METADATA
hdmf_docutils-0.4.9.dist-info/WHEEL
hdmf_docutils-0.4.9.dist-info/entry_points.txt
hdmf_docutils-0.4.9.dist-info/RECORD
