Metadata-Version: 2.4
Name: hdmf_docutils
Version: 0.4.9
Summary: Collection of CLIs, scripts and modules useful to generate the NWB documentation
Project-URL: Homepage, https://github.com/hdmf-dev/hdmf-docutils
Author-email: Oliver Ruebel <oruebel@lbl.gov>, Ryan Ly <rly@lbl.gov>
License-Expression: BSD-3-Clause-LBNL
Keywords: HDF,HDF5,NWB,NWB:N,NeurodataWithoutBorders,Neuroscience,cross-platform,data-format,open-data,open-science,open-source,python,reproducible-research
Classifier: Development Status :: 2 - Pre-Alpha
Classifier: Intended Audience :: Developers
Classifier: Intended Audience :: Science/Research
Classifier: License :: OSI Approved :: BSD License
Classifier: Operating System :: OS Independent
Classifier: Programming Language :: Python
Classifier: Programming Language :: Python :: 3.8
Classifier: Programming Language :: Python :: 3.9
Classifier: Programming Language :: Python :: 3.10
Classifier: Programming Language :: Python :: 3.11
Classifier: Programming Language :: Python :: 3.12
Classifier: Programming Language :: Python :: 3.13
Classifier: Topic :: Documentation :: Sphinx
Requires-Python: >=3.8
Requires-Dist: hdmf>=4.1.0
Requires-Dist: matplotlib
Requires-Dist: networkx
Requires-Dist: pillow
Requires-Dist: ruamel-yaml
Requires-Dist: sphinx
Requires-Dist: sphinx-gallery
Requires-Dist: sphinx-rtd-theme
Provides-Extra: dev
Requires-Dist: codespell; extra == 'dev'
Requires-Dist: pytest; extra == 'dev'
Requires-Dist: ruff; extra == 'dev'
